bufsock.py
bufsock-1.0.dist-info/COPYING
bufsock-1.0.dist-info/METADATA
bufsock-1.0.dist-info/WHEEL
bufsock-1.0.dist-info/top_level.txt
bufsock-1.0.dist-info/RECORD
